facexformer_pipeline/__init__.py
facexformer_pipeline/facexformer_pipeline.py
facexformer_pipeline/task_postprocesser.py
facexformer_pipeline/utils.py
facexformer_pipeline/network/__init__.py
facexformer_pipeline/network/models/__init__.py
facexformer_pipeline/network/models/facexformer.py
facexformer_pipeline/network/models/transformer.py
facexformer_pipeline-0.2.8.dist-info/METADATA
facexformer_pipeline-0.2.8.dist-info/WHEEL
facexformer_pipeline-0.2.8.dist-info/top_level.txt
facexformer_pipeline-0.2.8.dist-info/RECORD
