Metadata-Version: 2.1
Name: facexformer_pipeline
Version: 0.2.8
Summary: A module to run facexformer model as pipeline
Author: Enes Kuzucu
Classifier: Development Status :: 3 - Alpha
Classifier: Intended Audience :: Developers
Classifier: License :: OSI Approved :: MIT License
Classifier: Programming Language :: Python :: 3
Classifier: Programming Language :: Python :: 3.7
Classifier: Programming Language :: Python :: 3.8
Classifier: Programming Language :: Python :: 3.9
Classifier: Programming Language :: Python :: 3.10
Classifier: Operating System :: OS Independent
Requires-Python: >=3.7
Requires-Dist: numpy
Requires-Dist: opencv-python
Requires-Dist: image-input-handler
Requires-Dist: torchvision
Requires-Dist: facenet-pytorch
Requires-Dist: huggingface-hub
Requires-Dist: torch
